vncuda/CTPMarket.py
vncuda/CTPMarketType.py
vncuda/__init__.py
vncuda/globalType.py
vncuda/globalvar.py
vncuda/main.py
vnapi-1.0.dist-info/LICENSE
vnapi-1.0.dist-info/METADATA
vnapi-1.0.dist-info/WHEEL
vnapi-1.0.dist-info/top_level.txt
vnapi-1.0.dist-info/RECORD
